{"Title":"My Own Private Idaho","Year":"1991","Rated":"R","Released":"20 Jul 1991","Runtime":"104 min","Genre":"Drama","Director":"Gus Van Sant","Writer":"Gus Van Sant (screenplay)","Actors":"River Phoenix, Keanu Reeves, James Russo, William Richert","Plot":"Two best friends living on the streets of Portland as hustlers embark on a journey of self discovery and find their relationship stumbling along the way.","Language":"English, Italian, German","Country":"USA","Awards":"12 wins & 10 nominations.","Poster":"https://m.media-amazon.com/images/M/MV5BZDgxMGU3YTEtODEzOC00MGVlLTk4OWUtYmY0ODU0OTI1NmMxL2ltYWdlL2ltYWdlXkEyXkFqcGdeQXVyMTQxNzMzNDI@._V1_SX300.jpg","Ratings":[{"Source":"Internet Movie Database","Value":"7.1/10"},{"Source":"Rotten Tomatoes","Value":"79%"},{"Source":"Metacritic","Value":"77/100"}],"Metascore":"77","imdbRating":"7.1","imdbVotes":"51,205","imdbID":"tt0102494","Type":"movie","DVD":"29 Apr 2016","BoxOffice":"$6,401,336","Production":"New Line Cinema","Website":"N/A","Response":"True"}