{"Title":"A Serbian Film","Year":"2010","Rated":"NC-17","Released":"30 Sep 2011","Runtime":"104 min","Genre":"Horror, Mystery, Thriller","Director":"Srdjan Spasojevic","Writer":"Aleksandar Radivojevic (screenplay), Srdjan Spasojevic (screenplay)","Actors":"Srdjan 'Zika' Todorovic, Sergej Trifunovic, Jelena Gavrilovic, Slobodan Bestic","Plot":"An aging porn star agrees to participate in an \"art film\" in order to make a clean break from the business, only to discover that he has been drafted into making a pedophilia and necrophilia themed snuff film.","Language":"Serbian, English, Swedish","Country":"Serbia","Awards":"1 win & 3 nominations.","Poster":"https://m.media-amazon.com/images/M/MV5BMTU2NzI3OTk4M15BMl5BanBnXkFtZTcwMTEyNzIxNA@@._V1_SX300.jpg","Ratings":[{"Source":"Internet Movie Database","Value":"5.0/10"},{"Source":"Rotten Tomatoes","Value":"47%"}],"Metascore":"N/A","imdbRating":"5.0","imdbVotes":"57,758","imdbID":"tt1273235","Type":"movie","DVD":"19 Jan 2021","BoxOffice":"N/A","Production":"N/A","Website":"N/A","Response":"True"}