{"Title":"Ivan's Childhood","Year":"1962","Rated":"Not Rated","Released":"27 Jun 1963","Runtime":"84 min","Genre":"Drama, War","Director":"Andrei Tarkovsky, Eduard Abalov","Writer":"Vladimir Bogomolov (story \"Ivan\"), Vladimir Bogomolov (screenplay), Mikhail Papava (screenplay)","Actors":"Nikolay Burlyaev, Valentin Zubkov, Evgeniy Zharikov, Stepan Krylov","Plot":"In WW2, twelve year old Soviet orphan Ivan Bondarev works for the Soviet army as a scout behind the German lines and strikes a friendship with three sympathetic Soviet officers.","Language":"Russian, German","Country":"Soviet Union","Awards":"2 wins.","Poster":"https://m.media-amazon.com/images/M/MV5BYTYzYzBhYjQtNDQxYS00MmUwLTkyZjgtZWVkOWFjNzE5OTI2XkEyXkFqcGdeQXVyNjMxMjkwMjI@._V1_SX300.jpg","Ratings":[{"Source":"Internet Movie Database","Value":"8.1/10"},{"Source":"Rotten Tomatoes","Value":"100%"}],"Metascore":"N/A","imdbRating":"8.1","imdbVotes":"31,954","imdbID":"tt0056111","Type":"movie","DVD":"N/A","BoxOffice":"$22,168","Production":"Mosfilm, Tret&#39;e Tvorcheskoe Obedinenie","Website":"N/A","Response":"True"}