{"Title":"Loving","Year":"2016","Rated":"PG-13","Released":"04 Nov 2016","Runtime":"123 min","Genre":"Biography, Drama, Romance","Director":"Jeff Nichols","Writer":"Jeff Nichols, Nancy Buirski (based in part on the documentary 'The Loving Story' by)","Actors":"Ruth Negga, Joel Edgerton, Will Dalton, Dean Mumford","Plot":"The story of Richard and Mildred Loving, a couple whose arrest for interracial marriage in 1960s Virginia began a legal battle that would end with the Supreme Court's historic 1967 decision.","Language":"English","Country":"UK, USA","Awards":"Nominated for 1 Oscar. Another 25 wins & 85 nominations.","Poster":"https://m.media-amazon.com/images/M/MV5BMjE4NTI3NjIzOF5BMl5BanBnXkFtZTgwNjI0NTI5ODE@._V1_SX300.jpg","Ratings":[{"Source":"Internet Movie Database","Value":"7.0/10"},{"Source":"Rotten Tomatoes","Value":"88%"},{"Source":"Metacritic","Value":"79/100"}],"Metascore":"79","imdbRating":"7.0","imdbVotes":"32,033","imdbID":"tt4669986","Type":"movie","DVD":"24 Jan 2017","BoxOffice":"$7,751,969","Production":"Raindog Films, Big Beach, Augusta Films, Focus Features, Tri-State Pictures","Website":"N/A","Response":"True"}