{"Title":"A Room with a View","Year":"1985","Rated":"Not Rated","Released":"11 Apr 1986","Runtime":"117 min","Genre":"Drama, Romance","Director":"James Ivory","Writer":"E.M. Forster (novel), Ruth Prawer Jhabvala (screenplay)","Actors":"Maggie Smith, Helena Bonham Carter, Denholm Elliott, Julian Sands","Plot":"Lucy meets George in a Florence pensione and the two share a brief romance before Lucy returns home, where she becomes engaged to Cecil. However, it isn't long before George unexpectedly enters her life again.","Language":"English, Italian","Country":"UK","Awards":"Won 3 Oscars. Another 22 wins & 22 nominations.","Poster":"https://m.media-amazon.com/images/M/MV5BYTEyYmE0M2MtZDQ1OC00MGUxLWI4OGMtM2M1ZjIyNDI0Y2Q4XkEyXkFqcGdeQXVyNjQ2MjQ5NzM@._V1_SX300.jpg","Ratings":[{"Source":"Internet Movie Database","Value":"7.3/10"},{"Source":"Rotten Tomatoes","Value":"100%"},{"Source":"Metacritic","Value":"83/100"}],"Metascore":"83","imdbRating":"7.3","imdbVotes":"39,849","imdbID":"tt0091867","Type":"movie","DVD":"N/A","BoxOffice":"$20,966,644","Production":"Merchant Ivory Productions, National Film Finance Corporation, Goldcrest Films International","Website":"N/A","Response":"True"}