{"Title":"The Losers","Year":"2010","Rated":"PG-13","Released":"23 Apr 2010","Runtime":"97 min","Genre":"Action, Adventure, Crime, Mystery, Thriller","Director":"Sylvain White","Writer":"Peter Berg (screenplay), James Vanderbilt (screenplay), Andy Diggle (comic book series), Jock (comic book series)","Actors":"Jeffrey Dean Morgan, Zoe Saldana, Chris Evans, Idris Elba","Plot":"A CIA special forces team are betrayed and left for dead by their superiors, galvanizing them to mount an offensive on the CIA.","Language":"English, Spanish, Sanskrit","Country":"USA, France","Awards":"1 win & 7 nominations.","Poster":"https://m.media-amazon.com/images/M/MV5BMjU3MTU0NDI4Nl5BMl5BanBnXkFtZTcwMTE0NDMyMw@@._V1_SX300.jpg","Ratings":[{"Source":"Internet Movie Database","Value":"6.3/10"},{"Source":"Rotten Tomatoes","Value":"49%"},{"Source":"Metacritic","Value":"44/100"}],"Metascore":"44","imdbRating":"6.3","imdbVotes":"91,769","imdbID":"tt0480255","Type":"movie","DVD":"01 Feb 2012","BoxOffice":"$23,591,432","Production":"Warner Bros., Weed Road Pictures, Dark Castle Entertainment","Website":"N/A","Response":"True"}