{"Title":"Watership Down","Year":"1978","Rated":"PG","Released":"01 Nov 1978","Runtime":"91 min","Genre":"Animation, Adventure, Drama, Thriller","Director":"Martin Rosen, John Hubley","Writer":"Richard Adams (novel), Martin Rosen","Actors":"John Hurt, Richard Briers, Michael Graham Cox, John Bennett","Plot":"Hoping to escape destruction by human developers and save their community, a colony of rabbits, led by Hazel and Fiver, seek out a safe place to set up a new warren.","Language":"English","Country":"UK","Awards":"1 win & 4 nominations.","Poster":"https://m.media-amazon.com/images/M/MV5BMzZiODUwNzktNzBiZi00MDc4LThkMGMtZmE3MTE0M2E1MTM3L2ltYWdlXkEyXkFqcGdeQXVyNTAyODkwOQ@@._V1_SX300.jpg","Ratings":[{"Source":"Internet Movie Database","Value":"7.6/10"},{"Source":"Rotten Tomatoes","Value":"82%"},{"Source":"Metacritic","Value":"64/100"}],"Metascore":"64","imdbRating":"7.6","imdbVotes":"33,737","imdbID":"tt0078480","Type":"movie","DVD":"11 Mar 2017","BoxOffice":"N/A","Production":"Warner Bros. Animation","Website":"N/A","Response":"True"}